carport/__init__.py
carport/_modidx.py
carport/core.py
carport/vis.py
carport-0.1.1.dist-info/LICENSE
carport-0.1.1.dist-info/METADATA
carport-0.1.1.dist-info/WHEEL
carport-0.1.1.dist-info/entry_points.txt
carport-0.1.1.dist-info/top_level.txt
carport-0.1.1.dist-info/RECORD
