Metadata-Version: 2.1
Name: carport
Version: 0.1.1
Summary: Dependency Graph from Python imports
Home-page: https://github.com/felidz/carport
Author: felidz
Author-email: cofelidz@outlook.com
License: Apache Software License 2.0
Keywords: nbdev jupyter notebook python
Classifier: Development Status :: 4 - Beta
Classifier: Intended Audience :: Developers
Classifier: Natural Language :: English
Classifier: Programming Language :: Python :: 3.7
Classifier: Programming Language :: Python :: 3.8
Classifier: Programming Language :: Python :: 3.9
Classifier: Programming Language :: Python :: 3.10
Classifier: License :: OSI Approved :: Apache Software License
Requires-Python: >=3.7
License-File: LICENSE
Requires-Dist: fastcore
Requires-Dist: pandas
Requires-Dist: graphviz
Requires-Dist: kroki
Requires-Dist: networkx
Provides-Extra: dev
